niltype/__init__.py
niltype/_nilable.py
niltype/_niltype.py
niltype/_version.py
niltype/py.typed
niltype-1.0.1.dist-info/LICENSE
niltype-1.0.1.dist-info/METADATA
niltype-1.0.1.dist-info/WHEEL
niltype-1.0.1.dist-info/top_level.txt
niltype-1.0.1.dist-info/RECORD
