Metadata-Version: 2.1
Name: niltype
Version: 1.0.1
Summary: A singleton Nil object to represent missing values when None is a valid data value
Home-page: https://github.com/tsv1/niltype
Author: Nikita Tsvetkov
Author-email: tsv1@fastmail.com
License: MIT
Classifier: License :: OSI Approved :: MIT License
Classifier: Programming Language :: Python :: 3.8
Classifier: Programming Language :: Python :: 3.9
Classifier: Programming Language :: Python :: 3.10
Classifier: Programming Language :: Python :: 3.11
Classifier: Programming Language :: Python :: 3.12
Classifier: Typing :: Typed
Requires-Python: >=3.8
License-File: LICENSE
